ChengxuyuanRuheYouyaDeZhengLinghuaqian20Fix1/README.md
ChengxuyuanRuheYouyaDeZhengLinghuaqian20Fix1/__init__.py
ChengxuyuanRuheYouyaDeZhengLinghuaqian20Fix1/__main__.py
ChengxuyuanRuheYouyaDeZhengLinghuaqian20Fix1/file.epub
ChengxuyuanRuheYouyaDeZhengLinghuaqian20Fix1/index.html
ChengxuyuanRuheYouyaDeZhengLinghuaqian20Fix1/css/__init__.py
ChengxuyuanRuheYouyaDeZhengLinghuaqian20Fix1/css/annotations.css
ChengxuyuanRuheYouyaDeZhengLinghuaqian20Fix1/css/main.css
ChengxuyuanRuheYouyaDeZhengLinghuaqian20Fix1/css/normalize.css
ChengxuyuanRuheYouyaDeZhengLinghuaqian20Fix1/css/popup.css
ChengxuyuanRuheYouyaDeZhengLinghuaqian20Fix1/font/__init__.py
ChengxuyuanRuheYouyaDeZhengLinghuaqian20Fix1/font/fontello.eot
ChengxuyuanRuheYouyaDeZhengLinghuaqian20Fix1/font/fontello.svg
ChengxuyuanRuheYouyaDeZhengLinghuaqian20Fix1/font/fontello.ttf
ChengxuyuanRuheYouyaDeZhengLinghuaqian20Fix1/font/fontello.woff
ChengxuyuanRuheYouyaDeZhengLinghuaqian20Fix1/img/__init__.py
ChengxuyuanRuheYouyaDeZhengLinghuaqian20Fix1/img/annotator-glyph-sprite.png
ChengxuyuanRuheYouyaDeZhengLinghuaqian20Fix1/img/annotator-icon-sprite.png
ChengxuyuanRuheYouyaDeZhengLinghuaqian20Fix1/img/apple-touch-icon.png
ChengxuyuanRuheYouyaDeZhengLinghuaqian20Fix1/img/cancelfullscreen.png
ChengxuyuanRuheYouyaDeZhengLinghuaqian20Fix1/img/close.png
ChengxuyuanRuheYouyaDeZhengLinghuaqian20Fix1/img/fullscreen.png
ChengxuyuanRuheYouyaDeZhengLinghuaqian20Fix1/img/loader.gif
ChengxuyuanRuheYouyaDeZhengLinghuaqian20Fix1/img/menu-icon.png
ChengxuyuanRuheYouyaDeZhengLinghuaqian20Fix1/img/save.png
ChengxuyuanRuheYouyaDeZhengLinghuaqian20Fix1/img/saved.png
ChengxuyuanRuheYouyaDeZhengLinghuaqian20Fix1/img/settings-s.png
ChengxuyuanRuheYouyaDeZhengLinghuaqian20Fix1/img/settings.png
ChengxuyuanRuheYouyaDeZhengLinghuaqian20Fix1/img/star.png
ChengxuyuanRuheYouyaDeZhengLinghuaqian20Fix1/js/__init__.py
ChengxuyuanRuheYouyaDeZhengLinghuaqian20Fix1/js/epub.js
ChengxuyuanRuheYouyaDeZhengLinghuaqian20Fix1/js/epub.min.js
chengxuyuan_ruhe_youya_de_zheng_linghuaqian_2_0_fix1-2025.3.24.1.dist-info/METADATA
chengxuyuan_ruhe_youya_de_zheng_linghuaqian_2_0_fix1-2025.3.24.1.dist-info/WHEEL
chengxuyuan_ruhe_youya_de_zheng_linghuaqian_2_0_fix1-2025.3.24.1.dist-info/entry_points.txt
chengxuyuan_ruhe_youya_de_zheng_linghuaqian_2_0_fix1-2025.3.24.1.dist-info/top_level.txt
chengxuyuan_ruhe_youya_de_zheng_linghuaqian_2_0_fix1-2025.3.24.1.dist-info/RECORD
